qcir_sim/__init__.py
qcir_sim/exceptions.py
qcir_sim/simulation.py
qcir_sim/utils.py
qcir_sim-0.1.0.dist-info/METADATA
qcir_sim-0.1.0.dist-info/WHEEL
qcir_sim-0.1.0.dist-info/licenses/LICENSE
qcir_sim-0.1.0.dist-info/RECORD
