Metadata-Version: 2.3
Name: qcir-sim
Version: 0.1.0
Summary: Quantum circuit simulation
Requires-Python: >=3.12
Requires-Dist: numpy>=2.1.2
